kain/__init__.py
kain/classes.py
kain/descriptors.py
kain/importer.py
kain/internals.py
kain/monkey.py
kain/signals.py
kain-0.1.5.dist-info/METADATA
kain-0.1.5.dist-info/WHEEL
kain-0.1.5.dist-info/top_level.txt
kain-0.1.5.dist-info/RECORD
