Metadata-Version: 2.4
Name: kain
Version: 0.1.5
Summary: kain
Author-email: Alex Kalaverin <alex@kalaver.in>
Project-URL: Homepage, https://kalaver.in
Classifier: Intended Audience :: Developers
Classifier: Programming Language :: Python
Classifier: Programming Language :: Python :: 3
Classifier: Programming Language :: Python :: 3.10
Classifier: Programming Language :: Python :: 3.11
Classifier: License :: OSI Approved :: BSD License
Classifier: Operating System :: OS Independent
Requires-Python: <3.13,>=3.10
